<?xml version="1.0" encoding="UTF-8"?>
<GenRun Id="fix_float_synth_1" LaunchPart="xc7z010clg400-1" LaunchTime="1676388992">
  <File Type="PA-TCL" Name="fix_float.tcl"/>
  <File Type="REPORTS-TCL" Name="fix_float_reports.tcl"/>
  <File Type="RDS-RDS" Name="fix_float.vds"/>
  <File Type="RDS-UTIL" Name="fix_float_utilization_synth.rpt"/>
  <File Type="RDS-UTIL-PB" Name="fix_float_utilization_synth.pb"/>
  <File Type="RDS-DCP" Name="fix_float.dcp"/>
  <FileSet Name="sources" Type="BlockSrcs" RelSrcDir="$PSRCDIR/fix_float">
    <File Path="$PSRCDIR/sources_1/ip/fix_float/fix_float.xci">
      <FileInfo>
        <Attr Name="ImportPath" Val="$PPRDIR/../ov5640_mnist/ov5640_mnist.srcs/sources_1/ip/fix_float/fix_float.xci"/>
        <Attr Name="ImportTime" Val="1677770161"/>
        <Attr Name="UsedIn" Val="synthesis"/>
        <Attr Name="UsedIn" Val="implementation"/>
        <Attr Name="UsedIn" Val="simulation"/>
      </FileInfo>
    </File>
    <File Path="$PSRCDIR/sources_1/ip/fix_float.xcix">
      <FileInfo>
        <Attr Name="ImportPath" Val="$PPRDIR/../ov5640_mnist/ov5640_mnist.srcs/sources_1/ip/fix_float.xcix"/>
        <Attr Name="ImportTime" Val="1676389043"/>
        <Attr Name="UsedIn" Val="synthesis"/>
        <Attr Name="UsedIn" Val="implementation"/>
        <Attr Name="UsedIn" Val="simulation"/>
      </FileInfo>
    </File>
    <Config>
      <Option Name="TopModule" Val="fix_float"/>
      <Option Name="UseBlackboxStub" Val="1"/>
    </Config>
  </FileSet>
  <FileSet Name="constrs_in" Type="BlockSrcs" RelSrcDir="$PSRCDIR/fix_float">
    <File Path="$PSRCDIR/sources_1/ip/fix_float/fix_float.xci">
      <FileInfo>
        <Attr Name="ImportPath" Val="$PPRDIR/../ov5640_mnist/ov5640_mnist.srcs/sources_1/ip/fix_float/fix_float.xci"/>
        <Attr Name="ImportTime" Val="1677770161"/>
        <Attr Name="UsedIn" Val="synthesis"/>
        <Attr Name="UsedIn" Val="implementation"/>
        <Attr Name="UsedIn" Val="simulation"/>
      </FileInfo>
    </File>
    <File Path="$PSRCDIR/sources_1/ip/fix_float.xcix">
      <FileInfo>
        <Attr Name="ImportPath" Val="$PPRDIR/../ov5640_mnist/ov5640_mnist.srcs/sources_1/ip/fix_float.xcix"/>
        <Attr Name="ImportTime" Val="1676389043"/>
        <Attr Name="UsedIn" Val="synthesis"/>
        <Attr Name="UsedIn" Val="implementation"/>
        <Attr Name="UsedIn" Val="simulation"/>
      </FileInfo>
    </File>
    <Config>
      <Option Name="TopModule" Val="fix_float"/>
      <Option Name="UseBlackboxStub" Val="1"/>
    </Config>
  </FileSet>
  <Strategy Version="1" Minor="2">
    <StratHandle Name="Vivado Synthesis Defaults" Flow="Vivado Synthesis 2017"/>
    <Step Id="synth_design"/>
  </Strategy>
</GenRun>
